{"cameraMode":{"drawMode":0,"name":"Shaded","section":"Shading Mode"},"sceneLighting":true,"audioPlay":false,"sceneViewState":{"m_AlwaysRefresh":false,"showFog":true,"showSkybox":true,"showFlares":true,"showImageEffects":true,"showParticleSystems":true,"showVisualEffectGraphs":true,"m_FxEnabled":true},"in2DMode":false,"pivot":{"x":28.903705596923829,"y":4.99560546875,"z":70.81767272949219},"rotation":{"x":0.2096017599105835,"y":0.7708587050437927,"z":-0.5122597217559815,"w":0.31552621722221377},"size":28.41655731201172,"orthographic":false}